[{"fields": {"name": "within-category-glass", "num_questions_per_player": 10}, "model": "ratings.survey", "pk": 1}, {"fields": {"name": "within-category-tear", "num_questions_per_player": 10}, "model": "ratings.survey", "pk": 2}, {"fields": {"name": "within-category-water", "num_questions_per_player": 10}, "model": "ratings.survey", "pk": 3}, {"fields": {"name": "within-category-zipper", "num_questions_per_player": 10}, "model": "ratings.survey", "pk": 4}, {"fields": {"name": "between-4", "num_questions_per_player": 10}, "model": "ratings.survey", "pk": 5}, {"fields": {"name": "between-3", "num_questions_per_player": 10}, "model": "ratings.survey", "pk": 6}, {"fields": {"name": "between-2", "num_questions_per_player": 10}, "model": "ratings.survey", "pk": 7}, {"fields": {"name": "between-1", "num_questions_per_player": 10}, "model": "ratings.survey", "pk": 8}, {"fields": {"name": "test", "num_questions_per_player": 10}, "model": "ratings.survey", "pk": 9}, {"fields": {"name": "same-1", "num_questions_per_player": 10}, "model": "ratings.survey", "pk": 10}, {"fields": {"name": "same-2", "num_questions_per_player": 10}, "model": "ratings.survey", "pk": 11}, {"fields": {"name": "same-3", "num_questions_per_player": 10}, "model": "ratings.survey", "pk": 12}, {"fields": {"name": "same-4", "num_questions_per_player": 10}, "model": "ratings.survey", "pk": 13}, {"fields": {"name": "between-1-missing", "num_questions_per_player": 3}, "model": "ratings.survey", "pk": 14}, {"fields": {"name": "between-2-missing", "num_questions_per_player": 5}, "model": "ratings.survey", "pk": 15}, {"fields": {"name": "between-3-missing", "num_questions_per_player": 5}, "model": "ratings.survey", "pk": 16}, {"fields": {"name": "between-4-missing", "num_questions_per_player": 3}, "model": "ratings.survey", "pk": 17}, {"fields": {"name": "same-1-missing", "num_questions_per_player": 7}, "model": "ratings.survey", "pk": 18}, {"fields": {"name": "same-2-missing", "num_questions_per_player": 7}, "model": "ratings.survey", "pk": 19}, {"fields": {"name": "same-3-missing", "num_questions_per_player": 9}, "model": "ratings.survey", "pk": 20}, {"fields": {"name": "same-4-missing", "num_questions_per_player": 11}, "model": "ratings.survey", "pk": 21}]